Jenkinsfile
MANIFEST.in
Makefile
README.md
build.parameters
cakes.spec
mypy.ini
pyproject.toml
setup.cfg
tox.ini
src/cakes/__init__.py
src/cakes/client.py
src/cakes/py.typed
src/cakes/server.py
src/cakes/types.py
src/cakes/util.py
src/cakes.egg-info/PKG-INFO
src/cakes.egg-info/SOURCES.txt
src/cakes.egg-info/dependency_links.txt
src/cakes.egg-info/requires.txt
src/cakes.egg-info/top_level.txt
src/cakes/proto/__init__.py
src/cakes/proto/cakes_grpc.py
src/cakes/proto/cakes_pb2.py
src/cakes/proto/cakes_pb2_grpc.py
tests/conftest.py
tests/test_protocol.py