Metadata-Version: 2.1
Name: cakes
Version: 0.1.6
Summary: Certificate authority kit, ECDH-powered, SAS-authenticated
Home-page: https://github.com/Rudd-O/hassmpris
Author: Manuel Amador (Rudd-O)
Author-email: rudd-o@rudd-o.com
Classifier: Programming Language :: Python :: 3
Classifier: License :: OSI Approved :: GNU Lesser General Public License v2 (LGPLv2)
